throttling/__init__.py
throttling/admin.py
throttling/consts.py
throttling/decorators.py
throttling/managers.py
throttling/models.py
throttling/utils.py
throttling/migrations/0001_initial.py
throttling/migrations/__init__.py
throttling-1.2.0.dist-info/DESCRIPTION.rst
throttling-1.2.0.dist-info/METADATA
throttling-1.2.0.dist-info/metadata.json
throttling-1.2.0.dist-info/RECORD
throttling-1.2.0.dist-info/top_level.txt
throttling-1.2.0.dist-info/WHEEL
