Metadata-Version: 2.0
Name: throttling
Version: 1.2.0
Summary: Throttling system for Django views.
Home-page: https://github.com/laginha/django-throttling
Author: Diogo Laginha
Author-email: diogo.laginha.machado@gmail.com
License: MIT
Platform: UNKNOWN
Classifier: License :: OSI Approved :: MIT License
Classifier: Programming Language :: Python :: 2
Classifier: Intended Audience :: Developers
Requires-Dist: django
Requires-Dist: custom-user-roles
